respcode_mcp/__init__.py
respcode_mcp/server.py
respcode_mcp-2.1.2.dist-info/METADATA
respcode_mcp-2.1.2.dist-info/WHEEL
respcode_mcp-2.1.2.dist-info/entry_points.txt
respcode_mcp-2.1.2.dist-info/RECORD
