Metadata-Version: 2.4
Name: respcode-mcp
Version: 2.1.2
Summary: MCP Server for RespCode - Multi-Architecture Code Execution
Project-URL: Homepage, https://respcode.com
Project-URL: Documentation, https://docs.respcode.com
Project-URL: Repository, https://github.com/RespCodeAI/respcode-mcp
Author-email: Noor <support@respcode.com>
License: MIT
Keywords: ai,anthropic,claude,code-execution,mcp
Classifier: Development Status :: 4 - Beta
Classifier: Intended Audience :: Developers
Classifier: License :: OSI Approved :: MIT License
Classifier: Programming Language :: Python :: 3.10
Classifier: Programming Language :: Python :: 3.11
Classifier: Programming Language :: Python :: 3.12
Requires-Python: >=3.10
Requires-Dist: httpx>=0.25.0
Requires-Dist: mcp>=1.0.0
